mx/__init__.py
mx/__version__.py
mx/app.py
mx/cli.py
mx/config.py
mx/notes.py
mx/static/app.css
mx/static/app.css.map
mx/static/edit.js
mx/static/favicon.svg
mx/static/style.css
mx/static/uikit-icons.js
mx/static/uikit.js
mx_notes-0.0.3.dist-info/LICENSE
mx_notes-0.0.3.dist-info/METADATA
mx_notes-0.0.3.dist-info/WHEEL
mx_notes-0.0.3.dist-info/entry_points.txt
mx_notes-0.0.3.dist-info/top_level.txt
mx_notes-0.0.3.dist-info/RECORD
